kortical/COPYRIGHT
kortical/VERSION
kortical/__init__.py
kortical/notes.txt
kortical/anonymization/__init__.py
kortical/anonymization/_anonymization.py
kortical/api/__init__.py
kortical/api/_api.py
kortical/api/app.py
kortical/api/app_instance.py
kortical/api/app_version.py
kortical/api/code.py
kortical/api/component_instance.py
kortical/api/cronjob.py
kortical/api/data.py
kortical/api/enums.py
kortical/api/environment.py
kortical/api/experiment_framework.py
kortical/api/model.py
kortical/api/model_instance.py
kortical/api/model_version.py
kortical/api/project.py
kortical/api/superhuman_calibration.py
kortical/api/worker_group.py
kortical/api/advanced/__init__.py
kortical/api/advanced/app.py
kortical/api/advanced/cronjob.py
kortical/api/advanced/data.py
kortical/api/advanced/model.py
kortical/api/advanced/project.py
kortical/api/advanced/worker_group.py
kortical/app/__init__.py
kortical/app/requests.py
kortical/app/template_helpers.py
kortical/cli/__init__.py
kortical/cli/_app.py
kortical/cli/_cmd_registry.py
kortical/cli/_component.py
kortical/cli/_config.py
kortical/cli/_cronjob.py
kortical/cli/_docker.py
kortical/cli/_environment.py
kortical/cli/_model.py
kortical/cli/_project.py
kortical/cli/_secret.py
kortical/cli/_status.py
kortical/cli/_storage.py
kortical/cli/_usage.py
kortical/cli/_worker.py
kortical/cli/helpers/__init__.py
kortical/cli/helpers/component_helpers.py
kortical/cli/helpers/environment_helpers.py
kortical/cli/helpers/kortical_config_helpers.py
kortical/cloud/__init__.py
kortical/cloud/cloud.py
kortical/cloud_api_app_templates/__init__.py
kortical/cloud_api_app_templates/automation_template/.gitignore
kortical/cloud_api_app_templates/automation_template/README.md
kortical/cloud_api_app_templates/automation_template/pytest.ini
kortical/cloud_api_app_templates/automation_template/requirements.txt
kortical/cloud_api_app_templates/automation_template/setup.py
kortical/cloud_api_app_templates/automation_template/.git_hooks/pre-commit
kortical-3.0.1.dist-info/METADATA
kortical-3.0.1.dist-info/WHEEL
kortical-3.0.1.dist-info/entry_points.txt
kortical-3.0.1.dist-info/top_level.txt
kortical-3.0.1.dist-info/RECORD
