Metadata-Version: 2.1
Name: kortical
Version: 3.0.1
Summary: kortical: Useful packages to support developers and data scientists using Kortical
Home-page: UNKNOWN
License: UNKNOWN
Platform: UNKNOWN
Requires-Python: >=3.8
Requires-Dist: GitPython
Requires-Dist: PyYAML
Requires-Dist: colorama
Requires-Dist: cryptography
Requires-Dist: docopt
Requires-Dist: gitdb
Requires-Dist: kubernetes
Requires-Dist: markdownify
Requires-Dist: numpy
Requires-Dist: packaging
Requires-Dist: pandas
Requires-Dist: python-dateutil
Requires-Dist: requests
Requires-Dist: requests-toolbelt
Requires-Dist: scikit-learn
Requires-Dist: slack-sdk
Requires-Dist: spacy
Requires-Dist: texttable
Requires-Dist: tqdm
Requires-Dist: xxhash
